mcp_flight_search/__init__.py
mcp_flight_search/config.py
mcp_flight_search/server.py
mcp_flight_search/models/__init__.py
mcp_flight_search/models/schemas.py
mcp_flight_search/services/__init__.py
mcp_flight_search/services/search_service.py
mcp_flight_search/services/serpapi_client.py
mcp_flight_search/utils/__init__.py
mcp_flight_search/utils/logging.py
mcp_flight_search-0.2.1.dist-info/licenses/LICENSE
mcp_flight_search-0.2.1.dist-info/METADATA
mcp_flight_search-0.2.1.dist-info/WHEEL
mcp_flight_search-0.2.1.dist-info/entry_points.txt
mcp_flight_search-0.2.1.dist-info/top_level.txt
mcp_flight_search-0.2.1.dist-info/RECORD
