Metadata-Version: 2.4
Name: mcp-flight-search
Version: 0.2.1
Summary: Flight search service implementing  Model Context Protocol (MCP) tools
Author-email: Arjun Prabhulal <code.aicloudlab@gmail.com>
License-Expression: MIT
Project-URL: Homepage, https://github.com/arjunprabhulal/mcp-flight-search
Project-URL: Bug Tracker, https://github.com/arjunprabhulal/mcp-flight-search/issues
Classifier: Programming Language :: Python :: 3
Classifier: Operating System :: OS Independent
Requires-Python: >=3.7
License-File: LICENSE
Requires-Dist: fastmcp
Requires-Dist: google-search-results
Requires-Dist: rich
Requires-Dist: pydantic
Requires-Dist: python-dotenv
Dynamic: license-file
